Metadata-Version: 1.1
Name: git-hooks
Version: 0.0.3
Summary: Show useful git hooks
Home-page: https://github.com/juanpabloaj/git-hooks
Author: JuanPabloAJ
Author-email: jpabloaj@gmail.com
License: MIT
Platform: UNKNOWN
Classifier: Programming Language :: Python
Classifier: Programming Language :: Python :: 2.7
